bdw/__init__.py
bdw/check.py
bdw/delete.py
bdw/loader.py
bdw/replace.py
bdw/resurse/bwd_file_de
bdw/resurse/bwd_file_en
bdw/resurse/bwd_file_pl
bdw/resurse/bwd_file_ru
bdw/resurse/bwd_file_ua
bdw/resurse/de
bdw/resurse/en
bdw/resurse/pl
bdw/resurse/ru
bdw/resurse/ua
bdw-1.1.1.dist-info/LICENSE
bdw-1.1.1.dist-info/METADATA
bdw-1.1.1.dist-info/WHEEL
bdw-1.1.1.dist-info/top_level.txt
bdw-1.1.1.dist-info/RECORD
