Metadata-Version: 2.1
Name: bdw
Version: 1.1.1
Summary: This library is needed to check text for bad words in different languages.
Home-page: https://github.com/FlacSy/bdw
Author: FlacSy
Author-email: flacsy.x@gmail.com
License: UNKNOWN
Platform: UNKNOWN
Classifier: Programming Language :: Python :: 3
Classifier: License :: OSI Approved :: MIT License
Classifier: Operating System :: OS Independent
License-File: LICENSE
